{
  "version": "1.0.0",
  "restore": {
    "projectUniqueName": "C:\\Users\\Cem\\Documents\\identityrepo\\Generic_IntegratieProject\\DAL\\DAL.csproj",
    "projectName": "DAL",
    "projectPath": "C:\\Users\\Cem\\Documents\\identityrepo\\Generic_IntegratieProject\\DAL\\DAL.csproj",
    "outputPath": "C:\\Users\\Cem\\Documents\\identityrepo\\Generic_IntegratieProject\\DAL\\obj\\",
    "projectStyle": "PackageReference",
    "fallbackFolders": [
      "C:\\Program Files\\dotnet\\sdk\\NuGetFallbackFolder"
    ],
    "originalTargetFrameworks": [
      "netcoreapp2.2"
    ],
    "frameworks": {
      "netcoreapp2.2": {
        "projectReferences": {
          "C:\\Users\\Cem\\Documents\\identityrepo\\Generic_IntegratieProject\\Domain\\Domain.csproj": {
            "projectPath": "C:\\Users\\Cem\\Documents\\identityrepo\\Generic_IntegratieProject\\Domain\\Domain.csproj"
          }
        }
      }
    },
    "warningProperties": {
      "warnAsError": [
        "NU1605"
      ]
    }
  },
  "frameworks": {
    "netcoreapp2.2": {
      "dependencies": {
        "Microsoft.AspNetCore.Identity.EntityFrameworkCore": {
          "target": "Package",
          "version": "[2.2.0, )"
        },
        "Microsoft.EntityFrameworkCore": {
          "target": "Package",
          "version": "[2.2.2, )"
        },
        "Microsoft.EntityFrameworkCore.SqlServer": {
          "target": "Package",
          "version": "[2.2.2, )"
        },
        "Microsoft.EntityFrameworkCore.Sqlite": {
          "target": "Package",
          "version": "[2.2.2, )"
        },
        "Microsoft.NETCore.App": {
          "suppressParent": "All",
          "target": "Package",
          "version": "[2.2.0, )",
          "autoReferenced": true
        }
      },
      "imports": [
        "net461"
      ],
      "assetTargetFallback": true,
      "warn": true
    }
  }
}